CellScope/__init__.py
CellScope/cm.py
CellScope/cs.py
CellScope/fm.py
CellScope/ga.py
CellScope/gev.py
CellScope/ts.py
cellscope_rna-0.1.5.dist-info/METADATA
cellscope_rna-0.1.5.dist-info/WHEEL
cellscope_rna-0.1.5.dist-info/top_level.txt
cellscope_rna-0.1.5.dist-info/RECORD
