Metadata-Version: 2.4
Name: CellScope-RNA
Version: 0.1.5
Summary: A package for analyzing and visualizing gene expression data
Author: Tianhao Ni
Author-email: thni@zju.edu.cn
Classifier: Programming Language :: Python :: 3
Classifier: License :: OSI Approved :: MIT License
Classifier: Operating System :: OS Independent
Requires-Python: >=3.7, <3.11
Requires-Dist: anndata>=0.11.4
Requires-Dist: fastcluster>=1.2.6
Requires-Dist: joblib>=1.4.2
Requires-Dist: kaleido>=0.2.1
Requires-Dist: matplotlib>=3.10.1
Requires-Dist: nbformat>=5.10.4
Requires-Dist: networkx>=3.4.2
Requires-Dist: numba>=0.61.2
Requires-Dist: numpy<2.2,>=1.26.4
Requires-Dist: pandas>=2.2.3
Requires-Dist: plotly>=6.0.1
Requires-Dist: requests>=2.32.3
Requires-Dist: scikit-learn>=1.6.1
Requires-Dist: scipy>=1.13.1
Requires-Dist: seaborn>=0.13.2
Requires-Dist: statsmodels>=0.14.4
Requires-Dist: threadpoolctl>=3.6.0
Requires-Dist: umap-learn>=0.5.7
Dynamic: author
Dynamic: author-email
Dynamic: classifier
Dynamic: requires-dist
Dynamic: requires-python
Dynamic: summary
